async_generator/__init__.py
async_generator/_impl.py
async_generator/_util.py
async_generator/_version.py
async_generator/_tests/__init__.py
async_generator/_tests/conftest.py
async_generator/_tests/test_async_generator.py
async_generator/_tests/test_util.py
async_generator-1.9.dist-info/DESCRIPTION.rst
async_generator-1.9.dist-info/METADATA
async_generator-1.9.dist-info/RECORD
async_generator-1.9.dist-info/WHEEL
async_generator-1.9.dist-info/metadata.json
async_generator-1.9.dist-info/top_level.txt
