Metadata-Version: 1.2
Name: async-generator
Version: 1.9
Summary: Async generators and context managers for Python 3.5+
Home-page: https://github.com/python-trio/async_generator
Author: Nathaniel J. Smith
Author-email: njs@pobox.com
License: MIT
Keywords: async
Platform: UNKNOWN
Classifier: Development Status :: 5 - Production/Stable
Classifier: Intended Audience :: Developers
Classifier: License :: OSI Approved :: MIT License
Classifier: License :: OSI Approved :: Apache Software License
Classifier: Programming Language :: Python :: Implementation :: CPython
Classifier: Programming Language :: Python :: Implementation :: PyPy
Classifier: Programming Language :: Python :: 3 :: Only
Classifier: Programming Language :: Python :: 3.5
Classifier: Programming Language :: Python :: 3.6
Classifier: Framework :: AsyncIO
Requires-Python: >=3.5
